README.txt
setup.cfg
setup.py
collective/__init__.py
collective.sitecontacts.egg-info/PKG-INFO
collective.sitecontacts.egg-info/SOURCES.txt
collective.sitecontacts.egg-info/dependency_links.txt
collective.sitecontacts.egg-info/entry_points.txt
collective.sitecontacts.egg-info/namespace_packages.txt
collective.sitecontacts.egg-info/not-zip-safe
collective.sitecontacts.egg-info/paster_plugins.txt
collective.sitecontacts.egg-info/requires.txt
collective.sitecontacts.egg-info/top_level.txt
collective/sitecontacts/README.txt
collective/sitecontacts/__init__.py
collective/sitecontacts/browser.py
collective/sitecontacts/config.py
collective/sitecontacts/configure.zcml
collective/sitecontacts/contact.pt
collective/sitecontacts/contact.py
collective/sitecontacts/folder.pt
collective/sitecontacts/folder.py
collective/sitecontacts/i18n.py
collective/sitecontacts/interfaces.py
collective/sitecontacts/setuphandlers.py
collective/sitecontacts/tests.py
collective/sitecontacts/update_i18n.sh
collective/sitecontacts/locales/collective.sitecontacts.pot
collective/sitecontacts/locales/manual-collective.sitecontacts.pot
collective/sitecontacts/locales/cs/LC_MESSAGES/collective.sitecontacts.mo
collective/sitecontacts/locales/cs/LC_MESSAGES/collective.sitecontacts.po
collective/sitecontacts/locales/en/LC_MESSAGES/collective.sitecontacts.po
collective/sitecontacts/profiles/default/browserlayer.xml
collective/sitecontacts/profiles/default/collective.sitecontacts-install.txt
collective/sitecontacts/profiles/default/factorytool.xml
collective/sitecontacts/profiles/default/metadata.xml
collective/sitecontacts/profiles/default/rolemap.xml
collective/sitecontacts/profiles/default/types.xml
collective/sitecontacts/profiles/default/types/Contact.xml
collective/sitecontacts/profiles/default/types/ContactFolder.xml
docs/HISTORY.txt
docs/INSTALL.txt
docs/LICENSE.GPL
docs/LICENSE.txt