Metadata-Version: 1.0
Name: collective.sitecontacts
Version: 1.0
Summary: Simple contacts folder for your website based on Plone.
Home-page: http://svn.plone.org/svn/collective/
Author: UNKNOWN
Author-email: UNKNOWN
License: GPL
Platform: UNKNOWN
Classifier: Framework :: Plone
Classifier: Programming Language :: Python
